{
  "INDEP@1000": {
    "arm": "INDEP",
    "episode": 975,
    "val_total_cost": 79.57396835
  },
  "INDEP@2000": {
    "arm": "INDEP",
    "episode": 975,
    "val_total_cost": 79.57396835
  },
  "INDEP@500": {
    "arm": "INDEP",
    "episode": 300,
    "val_total_cost": 81.2627437
  },
  "QMIX@1000": {
    "arm": "QMIX",
    "episode": 775,
    "val_total_cost": 130.4967127
  },
  "QMIX@2000": {
    "arm": "QMIX",
    "episode": 1675,
    "val_total_cost": 128.3158797
  },
  "QMIX@500": {
    "arm": "QMIX",
    "episode": 350,
    "val_total_cost": 134.0766983
  }
}