[
  {
    "action_counts": {
      "PRE_REHANDLE": 5,
      "REPOSITION": 66,
      "SERVE": 48,
      "WAIT": 19
    },
    "backlog": 0,
    "cand_feasible": {
      "PRE_REHANDLE": 189,
      "REPOSITION": 375,
      "SERVE": 115,
      "WAIT": 138
    },
    "cand_listed": {
      "PRE_REHANDLE": 241,
      "REPOSITION": 449,
      "SERVE": 123,
      "WAIT": 138
    },
    "combo_truncations": 14,
    "completion_rate": 1.0,
    "empty_travel_m": 4699.5,
    "invariants_ok": true,
    "loaded_travel_m": 26.0,
    "mean_wait_min": 0.35114684805888396,
    "n_decisions": 89,
    "p95_wait_min": 2.431042344824482,
    "rehandles": 20,
    "seed": 420000,
    "serve_available": 102,
    "serve_taken": 48,
    "sts_wait_s": 49.93248727199807,
    "term_contrib": {
      "crane_travel": 0.026,
      "depart_delay": 0.0,
      "empty_travel": 4.6995000000000005,
      "imbalance": 0.268938,
      "interference": 12.64085737,
      "lane_cong": 46.4775278,
      "long_wait": 0.0,
      "rehandle": 4.0,
      "resequence": 0.0,
      "sts_wait": 0.08322081166666667,
      "transfer_wait": 0.3832208116666667,
      "truck_wait": 1.334358023333333,
      "vessel_delay": 0.0
    },
    "total_cost": 69.91362600000001,
    "transfer_wait_s": 229.93248727199807,
    "vessel_delay_min": 0.0
  },
  {
    "action_counts": {
      "PRE_REHANDLE": 7,
      "REPOSITION": 51,
      "SERVE": 41,
      "WAIT": 23
    },
    "backlog": 0,
    "cand_feasible": {
      "PRE_REHANDLE": 110,
      "REPOSITION": 239,
      "SERVE": 119,
      "WAIT": 122
    },
    "cand_listed": {
      "PRE_REHANDLE": 117,
      "REPOSITION": 250,
      "SERVE": 121,
      "WAIT": 122
    },
    "combo_truncations": 0,
    "completion_rate": 1.0,
    "empty_travel_m": 2353.0,
    "invariants_ok": true,
    "loaded_travel_m": 19.5,
    "mean_wait_min": 0.4587350716390901,
    "n_decisions": 66,
    "p95_wait_min": 2.7503290546736023,
    "rehandles": 13,
    "seed": 420001,
    "serve_available": 100,
    "serve_taken": 41,
    "sts_wait_s": 44.75703717558645,
    "term_contrib": {
      "crane_travel": 0.0195,
      "depart_delay": 0.0,
      "empty_travel": 2.353,
      "imbalance": 0.220038,
      "interference": 18.626321680000004,
      "lane_cong": 36.35327787999999,
      "long_wait": 0.0,
      "rehandle": 2.6,
      "resequence": 0.0,
      "sts_wait": 0.07459506166666666,
      "transfer_wait": 0.3745950616666667,
      "truck_wait": 1.5138257366666665,
      "vessel_delay": 0.0
    },
    "total_cost": 62.135158000000004,
    "transfer_wait_s": 224.75703717558645,
    "vessel_delay_min": 0.0
  },
  {
    "action_counts": {
      "PRE_REHANDLE": 1,
      "REPOSITION": 46,
      "SERVE": 44,
      "WAIT": 14
    },
    "backlog": 0,
    "cand_feasible": {
      "PRE_REHANDLE": 37,
      "REPOSITION": 245,
      "SERVE": 105,
      "WAIT": 105
    },
    "cand_listed": {
      "PRE_REHANDLE": 43,
      "REPOSITION": 266,
      "SERVE": 109,
      "WAIT": 105
    },
    "combo_truncations": 0,
    "completion_rate": 1.0,
    "empty_travel_m": 3406.0,
    "invariants_ok": true,
    "loaded_travel_m": 13.0,
    "mean_wait_min": 0.16389069460412495,
    "n_decisions": 60,
    "p95_wait_min": 1.2947213654380751,
    "rehandles": 7,
    "seed": 420002,
    "serve_available": 94,
    "serve_taken": 44,
    "sts_wait_s": 35.37360578479547,
    "term_contrib": {
      "crane_travel": 0.013,
      "depart_delay": 0.0,
      "empty_travel": 3.406,
      "imbalance": 0.20119600000000007,
      "interference": 9.72652005,
      "lane_cong": 35.98308338,
      "long_wait": 0.0,
      "rehandle": 1.4,
      "resequence": 0.0,
      "sts_wait": 0.05895601,
      "transfer_wait": 0.35895601,
      "truck_wait": 0.5900065016666668,
      "vessel_delay": 0.0
    },
    "total_cost": 51.737718,
    "transfer_wait_s": 215.37360578479547,
    "vessel_delay_min": 0.0
  },
  {
    "action_counts": {
      "PRE_REHANDLE": 7,
      "REPOSITION": 84,
      "SERVE": 53,
      "WAIT": 18
    },
    "backlog": 0,
    "cand_feasible": {
      "PRE_REHANDLE": 171,
      "REPOSITION": 523,
      "SERVE": 139,
      "WAIT": 162
    },
    "cand_listed": {
      "PRE_REHANDLE": 195,
      "REPOSITION": 574,
      "SERVE": 146,
      "WAIT": 162
    },
    "combo_truncations": 20,
    "completion_rate": 1.0,
    "empty_travel_m": 5076.5,
    "invariants_ok": true,
    "loaded_travel_m": 19.5,
    "mean_wait_min": 0.4446111609662828,
    "n_decisions": 97,
    "p95_wait_min": 2.4856717019067522,
    "rehandles": 16,
    "seed": 420003,
    "serve_available": 123,
    "serve_taken": 53,
    "sts_wait_s": 51.78988099729577,
    "term_contrib": {
      "crane_travel": 0.0195,
      "depart_delay": 0.0,
      "empty_travel": 5.076499999999999,
      "imbalance": 0.2725249999999999,
      "interference": 9.51106786,
      "lane_cong": 47.73075005999999,
      "long_wait": 0.0,
      "rehandle": 3.2,
      "resequence": 0.0,
      "sts_wait": 0.08631646833333334,
      "transfer_wait": 0.38631646833333333,
      "truck_wait": 2.000750225,
      "vessel_delay": 0.0
    },
    "total_cost": 68.283729,
    "transfer_wait_s": 231.78988099729577,
    "vessel_delay_min": 0.0
  },
  {
    "action_counts": {
      "PRE_REHANDLE": 1,
      "REPOSITION": 51,
      "SERVE": 43,
      "WAIT": 21
    },
    "backlog": 0,
    "cand_feasible": {
      "PRE_REHANDLE": 112,
      "REPOSITION": 278,
      "SERVE": 93,
      "WAIT": 116
    },
    "cand_listed": {
      "PRE_REHANDLE": 123,
      "REPOSITION": 307,
      "SERVE": 98,
      "WAIT": 116
    },
    "combo_truncations": 3,
    "completion_rate": 1.0,
    "empty_travel_m": 3477.5,
    "invariants_ok": true,
    "loaded_travel_m": 13.0,
    "mean_wait_min": 0.27640489213039277,
    "n_decisions": 70,
    "p95_wait_min": 2.7267352204631,
    "rehandles": 16,
    "seed": 420004,
    "serve_available": 87,
    "serve_taken": 43,
    "sts_wait_s": 51.06497355732881,
    "term_contrib": {
      "crane_travel": 0.013,
      "depart_delay": 0.0,
      "empty_travel": 3.477499999999997,
      "imbalance": 0.250035,
      "interference": 13.717685300000003,
      "lane_cong": 41.05800006,
      "long_wait": 0.0,
      "rehandle": 3.2,
      "resequence": 0.0,
      "sts_wait": 0.08510829,
      "transfer_wait": 0.38510829,
      "truck_wait": 0.9674171216666667,
      "vessel_delay": 0.0
    },
    "total_cost": 63.153856999999995,
    "transfer_wait_s": 231.0649735573288,
    "vessel_delay_min": 0.0
  },
  {
    "action_counts": {
      "PRE_REHANDLE": 2,
      "REPOSITION": 88,
      "SERVE": 56,
      "WAIT": 26
    },
    "backlog": 0,
    "cand_feasible": {
      "PRE_REHANDLE": 150,
      "REPOSITION": 592,
      "SERVE": 206,
      "WAIT": 172
    },
    "cand_listed": {
      "PRE_REHANDLE": 179,
      "REPOSITION": 656,
      "SERVE": 222,
      "WAIT": 172
    },
    "combo_truncations": 14,
    "completion_rate": 1.0,
    "empty_travel_m": 5908.5,
    "invariants_ok": true,
    "loaded_travel_m": 71.5,
    "mean_wait_min": 1.379234728151055,
    "n_decisions": 106,
    "p95_wait_min": 5.53514504913634,
    "rehandles": 23,
    "seed": 420005,
    "serve_available": 145,
    "serve_taken": 56,
    "sts_wait_s": 41.91502323543409,
    "term_contrib": {
      "crane_travel": 0.0715,
      "depart_delay": 0.0,
      "empty_travel": 5.9084999999999965,
      "imbalance": 0.312156,
      "interference": 13.18056649,
      "lane_cong": 53.80933336,
      "long_wait": 0.0,
      "rehandle": 4.6000000000000005,
      "resequence": 0.0,
      "sts_wait": 0.06985837166666667,
      "transfer_wait": 0.3698583716666667,
      "truck_wait": 6.34447975,
      "vessel_delay": 0.0
    },
    "total_cost": 84.66625500000002,
    "transfer_wait_s": 221.9150232354341,
    "vessel_delay_min": 0.0
  },
  {
    "action_counts": {
      "PRE_REHANDLE": 6,
      "REPOSITION": 69,
      "SERVE": 49,
      "WAIT": 18
    },
    "backlog": 0,
    "cand_feasible": {
      "PRE_REHANDLE": 209,
      "REPOSITION": 515,
      "SERVE": 147,
      "WAIT": 142
    },
    "cand_listed": {
      "PRE_REHANDLE": 239,
      "REPOSITION": 546,
      "SERVE": 160,
      "WAIT": 142
    },
    "combo_truncations": 26,
    "completion_rate": 1.0,
    "empty_travel_m": 3893.5,
    "invariants_ok": true,
    "loaded_travel_m": 26.0,
    "mean_wait_min": 0.658241762632463,
    "n_decisions": 87,
    "p95_wait_min": 5.503922125583768,
    "rehandles": 26,
    "seed": 420006,
    "serve_available": 99,
    "serve_taken": 49,
    "sts_wait_s": 64.82234174408586,
    "term_contrib": {
      "crane_travel": 0.026,
      "depart_delay": 0.0,
      "empty_travel": 3.8935,
      "imbalance": 0.27399399999999996,
      "interference": 6.75399717,
      "lane_cong": 49.766444459999995,
      "long_wait": 0.0,
      "rehandle": 5.200000000000002,
      "resequence": 0.0,
      "sts_wait": 0.10803723666666668,
      "transfer_wait": 0.432148945,
      "truck_wait": 2.5671428749999996,
      "vessel_delay": 0.0
    },
    "total_cost": 69.021264,
    "transfer_wait_s": 259.28936697634344,
    "vessel_delay_min": 0.0
  },
  {
    "action_counts": {
      "PRE_REHANDLE": 2,
      "REPOSITION": 72,
      "SERVE": 53,
      "WAIT": 24
    },
    "backlog": 0,
    "cand_feasible": {
      "PRE_REHANDLE": 154,
      "REPOSITION": 432,
      "SERVE": 162,
      "WAIT": 151
    },
    "cand_listed": {
      "PRE_REHANDLE": 171,
      "REPOSITION": 477,
      "SERVE": 185,
      "WAIT": 151
    },
    "combo_truncations": 17,
    "completion_rate": 1.0,
    "empty_travel_m": 5635.5,
    "invariants_ok": true,
    "loaded_travel_m": 32.5,
    "mean_wait_min": 0.696412774290646,
    "n_decisions": 95,
    "p95_wait_min": 4.4955369136861005,
    "rehandles": 19,
    "seed": 420007,
    "serve_available": 116,
    "serve_taken": 53,
    "sts_wait_s": 31.36984876578481,
    "term_contrib": {
      "crane_travel": 0.0325,
      "depart_delay": 0.0,
      "empty_travel": 5.635500000000002,
      "imbalance": 0.2642290000000001,
      "interference": 15.100321740000002,
      "lane_cong": 49.596583400000014,
      "long_wait": 0.0,
      "rehandle": 3.8000000000000007,
      "resequence": 0.0,
      "sts_wait": 0.05228308166666666,
      "transfer_wait": 0.3522830816666667,
      "truck_wait": 2.994574933333334,
      "vessel_delay": 0.0
    },
    "total_cost": 77.82827799999997,
    "transfer_wait_s": 211.3698487657848,
    "vessel_delay_min": 0.0
  },
  {
    "action_counts": {
      "PRE_REHANDLE": 3,
      "REPOSITION": 60,
      "SERVE": 45,
      "WAIT": 21
    },
    "backlog": 0,
    "cand_feasible": {
      "PRE_REHANDLE": 105,
      "REPOSITION": 345,
      "SERVE": 114,
      "WAIT": 129
    },
    "cand_listed": {
      "PRE_REHANDLE": 137,
      "REPOSITION": 418,
      "SERVE": 142,
      "WAIT": 129
    },
    "combo_truncations": 8,
    "completion_rate": 1.0,
    "empty_travel_m": 4192.5,
    "invariants_ok": true,
    "loaded_travel_m": 52.0,
    "mean_wait_min": 0.7535435942433653,
    "n_decisions": 84,
    "p95_wait_min": 3.871603136259,
    "rehandles": 19,
    "seed": 420008,
    "serve_available": 98,
    "serve_taken": 45,
    "sts_wait_s": 25.569676128434367,
    "term_contrib": {
      "crane_travel": 0.052,
      "depart_delay": 0.0,
      "empty_travel": 4.192499999999998,
      "imbalance": 0.26529200000000003,
      "interference": 14.756887849999998,
      "lane_cong": 43.75155561,
      "long_wait": 0.0,
      "rehandle": 3.8000000000000007,
      "resequence": 0.0,
      "sts_wait": 0.04261612666666667,
      "transfer_wait": 0.3426161283333333,
      "truck_wait": 2.63740258,
      "vessel_delay": 0.0
    },
    "total_cost": 69.84087800000002,
    "transfer_wait_s": 205.56967612843437,
    "vessel_delay_min": 0.0
  },
  {
    "action_counts": {
      "PRE_REHANDLE": 4,
      "REPOSITION": 66,
      "SERVE": 48,
      "WAIT": 18
    },
    "backlog": 0,
    "cand_feasible": {
      "PRE_REHANDLE": 143,
      "REPOSITION": 408,
      "SERVE": 116,
      "WAIT": 136
    },
    "cand_listed": {
      "PRE_REHANDLE": 176,
      "REPOSITION": 459,
      "SERVE": 128,
      "WAIT": 136
    },
    "combo_truncations": 12,
    "completion_rate": 1.0,
    "empty_travel_m": 4205.5,
    "invariants_ok": true,
    "loaded_travel_m": 39.0,
    "mean_wait_min": 0.3688562019062941,
    "n_decisions": 84,
    "p95_wait_min": 2.6823522235524555,
    "rehandles": 19,
    "seed": 420009,
    "serve_available": 100,
    "serve_taken": 48,
    "sts_wait_s": 42.32291474475642,
    "term_contrib": {
      "crane_travel": 0.039,
      "depart_delay": 0.0,
      "empty_travel": 4.205499999999999,
      "imbalance": 0.260604,
      "interference": 11.83185365,
      "lane_cong": 46.83222228999998,
      "long_wait": 0.0,
      "rehandle": 3.8000000000000007,
      "resequence": 0.0,
      "sts_wait": 0.07053819166666667,
      "transfer_wait": 0.37053819333333327,
      "truck_wait": 1.4754248083333334,
      "vessel_delay": 0.0
    },
    "total_cost": 68.885687,
    "transfer_wait_s": 222.32291474475642,
    "vessel_delay_min": 0.0
  },
  {
    "action_counts": {
      "PRE_REHANDLE": 9,
      "REPOSITION": 67,
      "SERVE": 49,
      "WAIT": 25
    },
    "backlog": 0,
    "cand_feasible": {
      "PRE_REHANDLE": 175,
      "REPOSITION": 478,
      "SERVE": 149,
      "WAIT": 150
    },
    "cand_listed": {
      "PRE_REHANDLE": 206,
      "REPOSITION": 542,
      "SERVE": 180,
      "WAIT": 150
    },
    "combo_truncations": 22,
    "completion_rate": 1.0,
    "empty_travel_m": 4654.0,
    "invariants_ok": true,
    "loaded_travel_m": 13.0,
    "mean_wait_min": 0.34450798353994583,
    "n_decisions": 93,
    "p95_wait_min": 1.6765697074684491,
    "rehandles": 19,
    "seed": 420010,
    "serve_available": 118,
    "serve_taken": 49,
    "sts_wait_s": 28.278601137726582,
    "term_contrib": {
      "crane_travel": 0.013,
      "depart_delay": 0.0,
      "empty_travel": 4.653999999999998,
      "imbalance": 0.259855,
      "interference": 15.15945662,
      "lane_cong": 47.216472289999984,
      "long_wait": 0.0,
      "rehandle": 3.8000000000000007,
      "resequence": 0.0,
      "sts_wait": 0.047131001666666665,
      "transfer_wait": 0.34713100166666666,
      "truck_wait": 1.2746795366666668,
      "vessel_delay": 0.0
    },
    "total_cost": 72.77173000000002,
    "transfer_wait_s": 208.27860113772658,
    "vessel_delay_min": 0.0
  },
  {
    "action_counts": {
      "PRE_REHANDLE": 3,
      "REPOSITION": 63,
      "SERVE": 47,
      "WAIT": 16
    },
    "backlog": 0,
    "cand_feasible": {
      "PRE_REHANDLE": 57,
      "REPOSITION": 364,
      "SERVE": 125,
      "WAIT": 129
    },
    "cand_listed": {
      "PRE_REHANDLE": 67,
      "REPOSITION": 399,
      "SERVE": 139,
      "WAIT": 129
    },
    "combo_truncations": 2,
    "completion_rate": 1.0,
    "empty_travel_m": 4264.0,
    "invariants_ok": true,
    "loaded_travel_m": 13.0,
    "mean_wait_min": 0.4865714040586767,
    "n_decisions": 79,
    "p95_wait_min": 3.1552340381585435,
    "rehandles": 12,
    "seed": 420011,
    "serve_available": 104,
    "serve_taken": 47,
    "sts_wait_s": 37.288910732475415,
    "term_contrib": {
      "crane_travel": 0.013,
      "depart_delay": 0.0,
      "empty_travel": 4.263999999999998,
      "imbalance": 0.22677199999999997,
      "interference": 7.3173391599999995,
      "lane_cong": 41.48708337999999,
      "long_wait": 0.0,
      "rehandle": 2.4,
      "resequence": 0.0,
      "sts_wait": 0.062148185,
      "transfer_wait": 0.362148185,
      "truck_wait": 1.8003141950000003,
      "vessel_delay": 0.0
    },
    "total_cost": 57.93280899999998,
    "transfer_wait_s": 217.28891073247541,
    "vessel_delay_min": 0.0
  },
  {
    "action_counts": {
      "PRE_REHANDLE": 6,
      "REPOSITION": 57,
      "SERVE": 41,
      "WAIT": 23
    },
    "backlog": 0,
    "cand_feasible": {
      "PRE_REHANDLE": 108,
      "REPOSITION": 408,
      "SERVE": 151,
      "WAIT": 127
    },
    "cand_listed": {
      "PRE_REHANDLE": 121,
      "REPOSITION": 439,
      "SERVE": 174,
      "WAIT": 127
    },
    "combo_truncations": 15,
    "completion_rate": 1.0,
    "empty_travel_m": 4309.5,
    "invariants_ok": true,
    "loaded_travel_m": 39.0,
    "mean_wait_min": 0.3452648121433739,
    "n_decisions": 74,
    "p95_wait_min": 2.4375,
    "rehandles": 17,
    "seed": 420012,
    "serve_available": 94,
    "serve_taken": 41,
    "sts_wait_s": 60.643153592212,
    "term_contrib": {
      "crane_travel": 0.039,
      "depart_delay": 0.0,
      "empty_travel": 4.309500000000001,
      "imbalance": 0.235823,
      "interference": 15.750444689999998,
      "lane_cong": 39.626555610000004,
      "long_wait": 0.0,
      "rehandle": 3.4000000000000012,
      "resequence": 0.0,
      "sts_wait": 0.10107192333333334,
      "transfer_wait": 0.4042876916666667,
      "truck_wait": 1.0703209183333335,
      "vessel_delay": 0.0
    },
    "total_cost": 64.937006,
    "transfer_wait_s": 242.572614368848,
    "vessel_delay_min": 0.0
  },
  {
    "action_counts": {
      "PRE_REHANDLE": 5,
      "REPOSITION": 66,
      "SERVE": 51,
      "WAIT": 29
    },
    "backlog": 0,
    "cand_feasible": {
      "PRE_REHANDLE": 173,
      "REPOSITION": 450,
      "SERVE": 172,
      "WAIT": 151
    },
    "cand_listed": {
      "PRE_REHANDLE": 195,
      "REPOSITION": 481,
      "SERVE": 189,
      "WAIT": 151
    },
    "combo_truncations": 18,
    "completion_rate": 1.0,
    "empty_travel_m": 4836.0,
    "invariants_ok": true,
    "loaded_travel_m": 26.0,
    "mean_wait_min": 1.1974875901022979,
    "n_decisions": 88,
    "p95_wait_min": 5.42200869286609,
    "rehandles": 17,
    "seed": 420013,
    "serve_available": 125,
    "serve_taken": 51,
    "sts_wait_s": 50.869880680780625,
    "term_contrib": {
      "crane_travel": 0.026,
      "depart_delay": 0.0,
      "empty_travel": 4.835999999999996,
      "imbalance": 0.2956270000000001,
      "interference": 19.133229189999998,
      "lane_cong": 48.10700007,
      "long_wait": 0.0,
      "rehandle": 3.400000000000001,
      "resequence": 0.0,
      "sts_wait": 0.08478313500000001,
      "transfer_wait": 0.384783135,
      "truck_wait": 5.149196633333334,
      "vessel_delay": 0.0
    },
    "total_cost": 81.41662200000003,
    "transfer_wait_s": 230.86988068078062,
    "vessel_delay_min": 0.0
  },
  {
    "action_counts": {
      "PRE_REHANDLE": 1,
      "REPOSITION": 70,
      "SERVE": 52,
      "WAIT": 21
    },
    "backlog": 0,
    "cand_feasible": {
      "PRE_REHANDLE": 89,
      "REPOSITION": 421,
      "SERVE": 186,
      "WAIT": 144
    },
    "cand_listed": {
      "PRE_REHANDLE": 110,
      "REPOSITION": 467,
      "SERVE": 215,
      "WAIT": 144
    },
    "combo_truncations": 8,
    "completion_rate": 1.0,
    "empty_travel_m": 4478.5,
    "invariants_ok": true,
    "loaded_travel_m": 19.5,
    "mean_wait_min": 0.463034099456132,
    "n_decisions": 87,
    "p95_wait_min": 2.8108333333333273,
    "rehandles": 11,
    "seed": 420014,
    "serve_available": 124,
    "serve_taken": 52,
    "sts_wait_s": 50.241744325604486,
    "term_contrib": {
      "crane_travel": 0.0195,
      "depart_delay": 0.0,
      "empty_travel": 4.478499999999998,
      "imbalance": 0.2622530000000001,
      "interference": 15.715149019999998,
      "lane_cong": 43.96580561000001,
      "long_wait": 0.0,
      "rehandle": 2.2000000000000006,
      "resequence": 0.0,
      "sts_wait": 0.08373623999999999,
      "transfer_wait": 0.38373624000000006,
      "truck_wait": 1.944743216666667,
      "vessel_delay": 0.0
    },
    "total_cost": 69.05343099999997,
    "transfer_wait_s": 230.2417443256045,
    "vessel_delay_min": 0.0
  },
  {
    "action_counts": {
      "PRE_REHANDLE": 5,
      "REPOSITION": 66,
      "SERVE": 54,
      "WAIT": 17
    },
    "backlog": 0,
    "cand_feasible": {
      "PRE_REHANDLE": 103,
      "REPOSITION": 435,
      "SERVE": 174,
      "WAIT": 142
    },
    "cand_listed": {
      "PRE_REHANDLE": 125,
      "REPOSITION": 488,
      "SERVE": 201,
      "WAIT": 142
    },
    "combo_truncations": 13,
    "completion_rate": 1.0,
    "empty_travel_m": 5265.0,
    "invariants_ok": true,
    "loaded_travel_m": 6.5,
    "mean_wait_min": 0.8040782485253429,
    "n_decisions": 87,
    "p95_wait_min": 3.430704215102014,
    "rehandles": 17,
    "seed": 420015,
    "serve_available": 119,
    "serve_taken": 54,
    "sts_wait_s": 30.830134293691117,
    "term_contrib": {
      "crane_travel": 0.0065,
      "depart_delay": 0.0,
      "empty_travel": 5.264999999999998,
      "imbalance": 0.288991,
      "interference": 13.847495140000001,
      "lane_cong": 50.322861169999996,
      "long_wait": 0.0,
      "rehandle": 3.4000000000000004,
      "resequence": 0.0,
      "sts_wait": 0.05138355666666667,
      "transfer_wait": 0.3513835566666667,
      "truck_wait": 3.537944295000001,
      "vessel_delay": 0.0
    },
    "total_cost": 77.07156400000002,
    "transfer_wait_s": 210.83013429369112,
    "vessel_delay_min": 0.0
  },
  {
    "action_counts": {
      "PRE_REHANDLE": 5,
      "REPOSITION": 68,
      "SERVE": 44,
      "WAIT": 14
    },
    "backlog": 0,
    "cand_feasible": {
      "PRE_REHANDLE": 95,
      "REPOSITION": 393,
      "SERVE": 154,
      "WAIT": 131
    },
    "cand_listed": {
      "PRE_REHANDLE": 110,
      "REPOSITION": 428,
      "SERVE": 171,
      "WAIT": 131
    },
    "combo_truncations": 12,
    "completion_rate": 1.0,
    "empty_travel_m": 5648.5,
    "invariants_ok": true,
    "loaded_travel_m": 39.0,
    "mean_wait_min": 0.8169768416200428,
    "n_decisions": 79,
    "p95_wait_min": 5.018052036943906,
    "rehandles": 15,
    "seed": 420016,
    "serve_available": 102,
    "serve_taken": 44,
    "sts_wait_s": 14.975355969607335,
    "term_contrib": {
      "crane_travel": 0.039,
      "depart_delay": 0.0,
      "empty_travel": 5.648499999999998,
      "imbalance": 0.23148500000000002,
      "interference": 7.586782680000001,
      "lane_cong": 41.93202783,
      "long_wait": 0.0,
      "rehandle": 3.0,
      "resequence": 0.0,
      "sts_wait": 0.024958926666666666,
      "transfer_wait": 0.32495892666666665,
      "truck_wait": 2.7777212616666667,
      "vessel_delay": 0.0
    },
    "total_cost": 61.565436999999974,
    "transfer_wait_s": 194.97535596960734,
    "vessel_delay_min": 0.0
  },
  {
    "action_counts": {
      "PRE_REHANDLE": 4,
      "REPOSITION": 37,
      "SERVE": 42,
      "WAIT": 17
    },
    "backlog": 0,
    "cand_feasible": {
      "PRE_REHANDLE": 83,
      "REPOSITION": 225,
      "SERVE": 94,
      "WAIT": 100
    },
    "cand_listed": {
      "PRE_REHANDLE": 98,
      "REPOSITION": 247,
      "SERVE": 105,
      "WAIT": 100
    },
    "combo_truncations": 3,
    "completion_rate": 1.0,
    "empty_travel_m": 2710.5,
    "invariants_ok": true,
    "loaded_travel_m": 58.5,
    "mean_wait_min": 0.23368869941104567,
    "n_decisions": 59,
    "p95_wait_min": 1.5446779622253417,
    "rehandles": 21,
    "seed": 420017,
    "serve_available": 84,
    "serve_taken": 42,
    "sts_wait_s": 34.88022811406972,
    "term_contrib": {
      "crane_travel": 0.058499999999999996,
      "depart_delay": 0.0,
      "empty_travel": 2.710499999999999,
      "imbalance": 0.238256,
      "interference": 18.290536590000002,
      "lane_cong": 42.37783337,
      "long_wait": 0.0,
      "rehandle": 4.200000000000001,
      "resequence": 0.0,
      "sts_wait": 0.05813371333333334,
      "transfer_wait": 0.3581337133333333,
      "truck_wait": 0.7945415783333334,
      "vessel_delay": 0.0
    },
    "total_cost": 69.08643700000002,
    "transfer_wait_s": 214.88022811406972,
    "vessel_delay_min": 0.0
  },
  {
    "action_counts": {
      "PRE_REHANDLE": 4,
      "REPOSITION": 46,
      "SERVE": 43,
      "WAIT": 16
    },
    "backlog": 0,
    "cand_feasible": {
      "PRE_REHANDLE": 88,
      "REPOSITION": 291,
      "SERVE": 100,
      "WAIT": 109
    },
    "cand_listed": {
      "PRE_REHANDLE": 98,
      "REPOSITION": 307,
      "SERVE": 104,
      "WAIT": 109
    },
    "combo_truncations": 6,
    "completion_rate": 1.0,
    "empty_travel_m": 3107.0,
    "invariants_ok": true,
    "loaded_travel_m": 26.0,
    "mean_wait_min": 0.5052365221562053,
    "n_decisions": 62,
    "p95_wait_min": 3.316290880550211,
    "rehandles": 16,
    "seed": 420018,
    "serve_available": 86,
    "serve_taken": 43,
    "sts_wait_s": 33.0896265572228,
    "term_contrib": {
      "crane_travel": 0.026,
      "depart_delay": 0.0,
      "empty_travel": 3.106999999999999,
      "imbalance": 0.23506700000000003,
      "interference": 13.876758050000001,
      "lane_cong": 40.44705558999999,
      "long_wait": 0.0,
      "rehandle": 3.2,
      "resequence": 0.0,
      "sts_wait": 0.05514937833333333,
      "transfer_wait": 0.3551493783333333,
      "truck_wait": 1.7683278266666667,
      "vessel_delay": 0.0
    },
    "total_cost": 63.07051,
    "transfer_wait_s": 213.0896265572228,
    "vessel_delay_min": 0.0
  },
  {
    "action_counts": {
      "PRE_REHANDLE": 7,
      "REPOSITION": 103,
      "SERVE": 55,
      "WAIT": 48
    },
    "backlog": 0,
    "cand_feasible": {
      "PRE_REHANDLE": 258,
      "REPOSITION": 676,
      "SERVE": 272,
      "WAIT": 213
    },
    "cand_listed": {
      "PRE_REHANDLE": 295,
      "REPOSITION": 755,
      "SERVE": 300,
      "WAIT": 213
    },
    "combo_truncations": 43,
    "completion_rate": 1.0,
    "empty_travel_m": 4134.0,
    "invariants_ok": true,
    "loaded_travel_m": 13.0,
    "mean_wait_min": 0.6319901264796051,
    "n_decisions": 125,
    "p95_wait_min": 2.3291666666666666,
    "rehandles": 16,
    "seed": 420019,
    "serve_available": 185,
    "serve_taken": 55,
    "sts_wait_s": 20.72590361078619,
    "term_contrib": {
      "crane_travel": 0.013,
      "depart_delay": 0.0,
      "empty_travel": 4.133999999999996,
      "imbalance": 0.28586100000000014,
      "interference": 13.138336700000002,
      "lane_cong": 48.8403056,
      "long_wait": 0.0,
      "rehandle": 3.2,
      "resequence": 0.0,
      "sts_wait": 0.03454317333333334,
      "transfer_wait": 0.33454317499999997,
      "truck_wait": 2.9703535933333347,
      "vessel_delay": 0.0
    },
    "total_cost": 72.95095700000005,
    "transfer_wait_s": 200.7259036107862,
    "vessel_delay_min": 0.0
  },
  {
    "action_counts": {
      "PRE_REHANDLE": 4,
      "REPOSITION": 70,
      "SERVE": 51,
      "WAIT": 11
    },
    "backlog": 0,
    "cand_feasible": {
      "PRE_REHANDLE": 91,
      "REPOSITION": 401,
      "SERVE": 111,
      "WAIT": 136
    },
    "cand_listed": {
      "PRE_REHANDLE": 109,
      "REPOSITION": 454,
      "SERVE": 115,
      "WAIT": 136
    },
    "combo_truncations": 5,
    "completion_rate": 1.0,
    "empty_travel_m": 4153.5,
    "invariants_ok": true,
    "loaded_travel_m": 13.0,
    "mean_wait_min": 0.22907906198836947,
    "n_decisions": 85,
    "p95_wait_min": 1.4285981947724091,
    "rehandles": 13,
    "seed": 420020,
    "serve_available": 101,
    "serve_taken": 51,
    "sts_wait_s": 19.196651533019576,
    "term_contrib": {
      "crane_travel": 0.013,
      "depart_delay": 0.0,
      "empty_travel": 4.153499999999999,
      "imbalance": 0.261633,
      "interference": 7.8825473200000005,
      "lane_cong": 43.88869448999999,
      "long_wait": 0.0,
      "rehandle": 2.6000000000000005,
      "resequence": 0.0,
      "sts_wait": 0.03199442,
      "transfer_wait": 0.3319944216666667,
      "truck_wait": 0.9392241550000001,
      "vessel_delay": 0.0
    },
    "total_cost": 60.102591999999994,
    "transfer_wait_s": 199.19665153301958,
    "vessel_delay_min": 0.0
  },
  {
    "action_counts": {
      "PRE_REHANDLE": 1,
      "REPOSITION": 65,
      "SERVE": 42,
      "WAIT": 20
    },
    "backlog": 0,
    "cand_feasible": {
      "PRE_REHANDLE": 103,
      "REPOSITION": 377,
      "SERVE": 123,
      "WAIT": 128
    },
    "cand_listed": {
      "PRE_REHANDLE": 127,
      "REPOSITION": 432,
      "SERVE": 138,
      "WAIT": 128
    },
    "combo_truncations": 11,
    "completion_rate": 1.0,
    "empty_travel_m": 3503.5,
    "invariants_ok": true,
    "loaded_travel_m": 26.0,
    "mean_wait_min": 0.45877970684044045,
    "n_decisions": 81,
    "p95_wait_min": 2.355723494561926,
    "rehandles": 17,
    "seed": 420021,
    "serve_available": 107,
    "serve_taken": 42,
    "sts_wait_s": 30.703712586677284,
    "term_contrib": {
      "crane_travel": 0.026,
      "depart_delay": 0.0,
      "empty_travel": 3.503499999999997,
      "imbalance": 0.22225300000000006,
      "interference": 16.58515749,
      "lane_cong": 38.83502781,
      "long_wait": 0.0,
      "rehandle": 3.400000000000001,
      "resequence": 0.0,
      "sts_wait": 0.051172855,
      "transfer_wait": 0.3511728550000001,
      "truck_wait": 1.4680950633333336,
      "vessel_delay": 0.0
    },
    "total_cost": 64.442384,
    "transfer_wait_s": 210.70371258667728,
    "vessel_delay_min": 0.0
  },
  {
    "action_counts": {
      "PRE_REHANDLE": 4,
      "REPOSITION": 66,
      "SERVE": 45,
      "WAIT": 14
    },
    "backlog": 0,
    "cand_feasible": {
      "PRE_REHANDLE": 98,
      "REPOSITION": 391,
      "SERVE": 117,
      "WAIT": 129
    },
    "cand_listed": {
      "PRE_REHANDLE": 122,
      "REPOSITION": 436,
      "SERVE": 125,
      "WAIT": 129
    },
    "combo_truncations": 3,
    "completion_rate": 1.0,
    "empty_travel_m": 4485.0,
    "invariants_ok": true,
    "loaded_travel_m": 19.5,
    "mean_wait_min": 0.6540280469618913,
    "n_decisions": 78,
    "p95_wait_min": 3.7427777777777766,
    "rehandles": 16,
    "seed": 420022,
    "serve_available": 101,
    "serve_taken": 45,
    "sts_wait_s": 49.48389583957669,
    "term_contrib": {
      "crane_travel": 0.0195,
      "depart_delay": 0.0,
      "empty_travel": 4.484999999999999,
      "imbalance": 0.24407399999999999,
      "interference": 11.12676914,
      "lane_cong": 42.00227784,
      "long_wait": 0.0,
      "rehandle": 3.2000000000000006,
      "resequence": 0.0,
      "sts_wait": 0.08247316,
      "transfer_wait": 0.3824731600000001,
      "truck_wait": 2.419903773333333,
      "vessel_delay": 0.0
    },
    "total_cost": 63.96248300000002,
    "transfer_wait_s": 229.4838958395767,
    "vessel_delay_min": 0.0
  },
  {
    "action_counts": {
      "PRE_REHANDLE": 4,
      "REPOSITION": 55,
      "SERVE": 45,
      "WAIT": 16
    },
    "backlog": 0,
    "cand_feasible": {
      "PRE_REHANDLE": 89,
      "REPOSITION": 257,
      "SERVE": 119,
      "WAIT": 120
    },
    "cand_listed": {
      "PRE_REHANDLE": 112,
      "REPOSITION": 305,
      "SERVE": 130,
      "WAIT": 120
    },
    "combo_truncations": 3,
    "completion_rate": 1.0,
    "empty_travel_m": 3887.0,
    "invariants_ok": true,
    "loaded_travel_m": 13.0,
    "mean_wait_min": 0.44579375215276656,
    "n_decisions": 76,
    "p95_wait_min": 3.9822067156952015,
    "rehandles": 17,
    "seed": 420023,
    "serve_available": 96,
    "serve_taken": 45,
    "sts_wait_s": 28.902268656674096,
    "term_contrib": {
      "crane_travel": 0.013,
      "depart_delay": 0.0,
      "empty_travel": 3.8869999999999987,
      "imbalance": 0.23089700000000002,
      "interference": 13.351737059999998,
      "lane_cong": 42.45141667999999,
      "long_wait": 0.0,
      "rehandle": 3.4000000000000004,
      "resequence": 0.0,
      "sts_wait": 0.04817044833333333,
      "transfer_wait": 0.34817045,
      "truck_wait": 1.5602781316666667,
      "vessel_delay": 0.0
    },
    "total_cost": 65.290671,
    "transfer_wait_s": 208.9022686566741,
    "vessel_delay_min": 0.0
  },
  {
    "action_counts": {
      "PRE_REHANDLE": 3,
      "REPOSITION": 43,
      "SERVE": 45,
      "WAIT": 19
    },
    "backlog": 0,
    "cand_feasible": {
      "PRE_REHANDLE": 92,
      "REPOSITION": 253,
      "SERVE": 122,
      "WAIT": 110
    },
    "cand_listed": {
      "PRE_REHANDLE": 109,
      "REPOSITION": 275,
      "SERVE": 142,
      "WAIT": 110
    },
    "combo_truncations": 13,
    "completion_rate": 1.0,
    "empty_travel_m": 3276.0,
    "invariants_ok": true,
    "loaded_travel_m": 32.5,
    "mean_wait_min": 1.2195311806628542,
    "n_decisions": 67,
    "p95_wait_min": 7.566337472056322,
    "rehandles": 17,
    "seed": 420024,
    "serve_available": 91,
    "serve_taken": 45,
    "sts_wait_s": 69.33565307378012,
    "term_contrib": {
      "crane_travel": 0.0325,
      "depart_delay": 0.0,
      "empty_travel": 3.276,
      "imbalance": 0.227671,
      "interference": 15.917607749999998,
      "lane_cong": 42.53425003,
      "long_wait": 0.0,
      "rehandle": 3.4000000000000004,
      "resequence": 0.0,
      "sts_wait": 0.11555942166666666,
      "transfer_wait": 0.462237685,
      "truck_wait": 4.26835913,
      "vessel_delay": 0.0
    },
    "total_cost": 70.23418299999999,
    "transfer_wait_s": 277.3426122951205,
    "vessel_delay_min": 0.0
  },
  {
    "action_counts": {
      "PRE_REHANDLE": 2,
      "REPOSITION": 70,
      "SERVE": 54,
      "WAIT": 16
    },
    "backlog": 0,
    "cand_feasible": {
      "PRE_REHANDLE": 152,
      "REPOSITION": 457,
      "SERVE": 123,
      "WAIT": 142
    },
    "cand_listed": {
      "PRE_REHANDLE": 166,
      "REPOSITION": 495,
      "SERVE": 133,
      "WAIT": 142
    },
    "combo_truncations": 12,
    "completion_rate": 1.0,
    "empty_travel_m": 4816.5,
    "invariants_ok": true,
    "loaded_travel_m": 19.5,
    "mean_wait_min": 0.6929212597513714,
    "n_decisions": 86,
    "p95_wait_min": 4.967856252372712,
    "rehandles": 17,
    "seed": 420025,
    "serve_available": 108,
    "serve_taken": 54,
    "sts_wait_s": 25.143462154174813,
    "term_contrib": {
      "crane_travel": 0.0195,
      "depart_delay": 0.0,
      "empty_travel": 4.816500000000001,
      "imbalance": 0.274847,
      "interference": 9.75138523,
      "lane_cong": 49.594027859999976,
      "long_wait": 0.0,
      "rehandle": 3.400000000000001,
      "resequence": 0.0,
      "sts_wait": 0.04190577,
      "transfer_wait": 0.3419057716666667,
      "truck_wait": 3.0488535433333332,
      "vessel_delay": 0.0
    },
    "total_cost": 71.28893,
    "transfer_wait_s": 205.1434621541748,
    "vessel_delay_min": 0.0
  },
  {
    "action_counts": {
      "PRE_REHANDLE": 6,
      "REPOSITION": 73,
      "SERVE": 54,
      "WAIT": 22
    },
    "backlog": 0,
    "cand_feasible": {
      "PRE_REHANDLE": 154,
      "REPOSITION": 509,
      "SERVE": 198,
      "WAIT": 155
    },
    "cand_listed": {
      "PRE_REHANDLE": 200,
      "REPOSITION": 605,
      "SERVE": 217,
      "WAIT": 155
    },
    "combo_truncations": 19,
    "completion_rate": 1.0,
    "empty_travel_m": 6103.5,
    "invariants_ok": true,
    "loaded_travel_m": 32.5,
    "mean_wait_min": 0.9523988183888918,
    "n_decisions": 101,
    "p95_wait_min": 3.6626859249972767,
    "rehandles": 30,
    "seed": 420026,
    "serve_available": 123,
    "serve_taken": 54,
    "sts_wait_s": 12.439439877890436,
    "term_contrib": {
      "crane_travel": 0.0325,
      "depart_delay": 0.0,
      "empty_travel": 6.103499999999999,
      "imbalance": 0.3212090000000002,
      "interference": 11.032075350000001,
      "lane_cong": 57.9138056,
      "long_wait": 0.0,
      "rehandle": 6.000000000000003,
      "resequence": 0.0,
      "sts_wait": 0.020732399999999998,
      "transfer_wait": 0.3207324,
      "truck_wait": 4.190554803333331,
      "vessel_delay": 0.0
    },
    "total_cost": 85.93511700000003,
    "transfer_wait_s": 192.43943987789044,
    "vessel_delay_min": 0.0
  },
  {
    "action_counts": {
      "PRE_REHANDLE": 7,
      "REPOSITION": 75,
      "SERVE": 50,
      "WAIT": 15
    },
    "backlog": 0,
    "cand_feasible": {
      "PRE_REHANDLE": 182,
      "REPOSITION": 487,
      "SERVE": 158,
      "WAIT": 147
    },
    "cand_listed": {
      "PRE_REHANDLE": 225,
      "REPOSITION": 568,
      "SERVE": 200,
      "WAIT": 147
    },
    "combo_truncations": 23,
    "completion_rate": 1.0,
    "empty_travel_m": 5863.0,
    "invariants_ok": true,
    "loaded_travel_m": 32.5,
    "mean_wait_min": 0.6888186281373276,
    "n_decisions": 97,
    "p95_wait_min": 4.746558635971762,
    "rehandles": 25,
    "seed": 420027,
    "serve_available": 105,
    "serve_taken": 50,
    "sts_wait_s": 29.01716791445233,
    "term_contrib": {
      "crane_travel": 0.0325,
      "depart_delay": 0.0,
      "empty_travel": 5.863,
      "imbalance": 0.3042760000000001,
      "interference": 9.941545159999999,
      "lane_cong": 52.83108339,
      "long_wait": 0.0,
      "rehandle": 5.000000000000002,
      "resequence": 0.0,
      "sts_wait": 0.04836194666666667,
      "transfer_wait": 0.34836194666666664,
      "truck_wait": 2.75527451,
      "vessel_delay": 0.0
    },
    "total_cost": 77.12440899999997,
    "transfer_wait_s": 209.01716791445233,
    "vessel_delay_min": 0.0
  },
  {
    "action_counts": {
      "PRE_REHANDLE": 6,
      "REPOSITION": 55,
      "SERVE": 45,
      "WAIT": 16
    },
    "backlog": 0,
    "cand_feasible": {
      "PRE_REHANDLE": 135,
      "REPOSITION": 353,
      "SERVE": 145,
      "WAIT": 122
    },
    "cand_listed": {
      "PRE_REHANDLE": 150,
      "REPOSITION": 386,
      "SERVE": 163,
      "WAIT": 122
    },
    "combo_truncations": 17,
    "completion_rate": 1.0,
    "empty_travel_m": 4036.5,
    "invariants_ok": true,
    "loaded_travel_m": 19.5,
    "mean_wait_min": 1.3927053928494901,
    "n_decisions": 73,
    "p95_wait_min": 10.087444698074494,
    "rehandles": 16,
    "seed": 420028,
    "serve_available": 96,
    "serve_taken": 45,
    "sts_wait_s": 30.393504680139813,
    "term_contrib": {
      "crane_travel": 0.0195,
      "depart_delay": 0.0,
      "empty_travel": 4.036500000000001,
      "imbalance": 0.22693999999999998,
      "interference": 7.25756753,
      "lane_cong": 43.243111160000005,
      "long_wait": 0.0,
      "rehandle": 3.1999999999999997,
      "resequence": 0.0,
      "sts_wait": 0.050655841666666666,
      "transfer_wait": 0.35065584166666663,
      "truck_wait": 4.874468868333334,
      "vessel_delay": 0.0
    },
    "total_cost": 63.25939699999999,
    "transfer_wait_s": 210.3935046801398,
    "vessel_delay_min": 0.0
  },
  {
    "action_counts": {
      "PRE_REHANDLE": 5,
      "REPOSITION": 56,
      "SERVE": 47,
      "WAIT": 21
    },
    "backlog": 0,
    "cand_feasible": {
      "PRE_REHANDLE": 164,
      "REPOSITION": 408,
      "SERVE": 145,
      "WAIT": 129
    },
    "cand_listed": {
      "PRE_REHANDLE": 182,
      "REPOSITION": 430,
      "SERVE": 161,
      "WAIT": 129
    },
    "combo_truncations": 18,
    "completion_rate": 1.0,
    "empty_travel_m": 4270.5,
    "invariants_ok": true,
    "loaded_travel_m": 39.0,
    "mean_wait_min": 0.5465804305450359,
    "n_decisions": 76,
    "p95_wait_min": 2.4932883672500337,
    "rehandles": 24,
    "seed": 420029,
    "serve_available": 97,
    "serve_taken": 47,
    "sts_wait_s": 53.312007587357584,
    "term_contrib": {
      "crane_travel": 0.039,
      "depart_delay": 0.0,
      "empty_travel": 4.2705,
      "imbalance": 0.286205,
      "interference": 12.299407100000002,
      "lane_cong": 48.37411115000002,
      "long_wait": 0.0,
      "rehandle": 4.800000000000001,
      "resequence": 0.0,
      "sts_wait": 0.08885334666666667,
      "transfer_wait": 0.38885334666666665,
      "truck_wait": 2.0223475933333335,
      "vessel_delay": 0.0
    },
    "total_cost": 72.569279,
    "transfer_wait_s": 233.31200758735758,
    "vessel_delay_min": 0.0
  },
  {
    "action_counts": {
      "PRE_REHANDLE": 4,
      "REPOSITION": 61,
      "SERVE": 48,
      "WAIT": 16
    },
    "backlog": 0,
    "cand_feasible": {
      "PRE_REHANDLE": 96,
      "REPOSITION": 397,
      "SERVE": 129,
      "WAIT": 129
    },
    "cand_listed": {
      "PRE_REHANDLE": 110,
      "REPOSITION": 435,
      "SERVE": 136,
      "WAIT": 129
    },
    "combo_truncations": 11,
    "completion_rate": 1.0,
    "empty_travel_m": 4368.0,
    "invariants_ok": true,
    "loaded_travel_m": 26.0,
    "mean_wait_min": 0.5515757406331779,
    "n_decisions": 77,
    "p95_wait_min": 5.590422045411595,
    "rehandles": 14,
    "seed": 420030,
    "serve_available": 108,
    "serve_taken": 48,
    "sts_wait_s": 5.051881825866076,
    "term_contrib": {
      "crane_travel": 0.026,
      "depart_delay": 0.0,
      "empty_travel": 4.368000000000002,
      "imbalance": 0.275494,
      "interference": 10.32955658,
      "lane_cong": 44.10980559999998,
      "long_wait": 0.0,
      "rehandle": 2.8,
      "resequence": 0.0,
      "sts_wait": 0.008419803333333333,
      "transfer_wait": 0.3084198033333333,
      "truck_wait": 2.095987815,
      "vessel_delay": 0.0
    },
    "total_cost": 64.321688,
    "transfer_wait_s": 185.05188182586608,
    "vessel_delay_min": 0.0
  },
  {
    "action_counts": {
      "PRE_REHANDLE": 5,
      "REPOSITION": 67,
      "SERVE": 48,
      "WAIT": 17
    },
    "backlog": 0,
    "cand_feasible": {
      "PRE_REHANDLE": 102,
      "REPOSITION": 447,
      "SERVE": 150,
      "WAIT": 137
    },
    "cand_listed": {
      "PRE_REHANDLE": 140,
      "REPOSITION": 511,
      "SERVE": 182,
      "WAIT": 137
    },
    "combo_truncations": 20,
    "completion_rate": 1.0,
    "empty_travel_m": 4303.0,
    "invariants_ok": true,
    "loaded_travel_m": 32.5,
    "mean_wait_min": 0.6053892369067778,
    "n_decisions": 86,
    "p95_wait_min": 2.5382901230323567,
    "rehandles": 19,
    "seed": 420031,
    "serve_available": 110,
    "serve_taken": 48,
    "sts_wait_s": 36.12339964298553,
    "term_contrib": {
      "crane_travel": 0.0325,
      "depart_delay": 0.0,
      "empty_travel": 4.302999999999997,
      "imbalance": 0.274024,
      "interference": 9.78912107,
      "lane_cong": 46.50572229999999,
      "long_wait": 0.0,
      "rehandle": 3.8000000000000007,
      "resequence": 0.0,
      "sts_wait": 0.060205666666666664,
      "transfer_wait": 0.36020566666666665,
      "truck_wait": 2.300479095,
      "vessel_delay": 0.0
    },
    "total_cost": 67.42526299999999,
    "transfer_wait_s": 216.12339964298553,
    "vessel_delay_min": 0.0
  },
  {
    "action_counts": {
      "PRE_REHANDLE": 5,
      "REPOSITION": 82,
      "SERVE": 56,
      "WAIT": 16
    },
    "backlog": 0,
    "cand_feasible": {
      "PRE_REHANDLE": 127,
      "REPOSITION": 520,
      "SERVE": 213,
      "WAIT": 159
    },
    "cand_listed": {
      "PRE_REHANDLE": 144,
      "REPOSITION": 562,
      "SERVE": 237,
      "WAIT": 159
    },
    "combo_truncations": 19,
    "completion_rate": 1.0,
    "empty_travel_m": 5934.5,
    "invariants_ok": true,
    "loaded_travel_m": 39.0,
    "mean_wait_min": 0.46778616037086346,
    "n_decisions": 96,
    "p95_wait_min": 1.8683532389352877,
    "rehandles": 23,
    "seed": 420032,
    "serve_available": 127,
    "serve_taken": 56,
    "sts_wait_s": 65.00249679116041,
    "term_contrib": {
      "crane_travel": 0.039,
      "depart_delay": 0.0,
      "empty_travel": 5.934499999999997,
      "imbalance": 0.30631499999999995,
      "interference": 10.91796571,
      "lane_cong": 54.625777860000014,
      "long_wait": 0.0,
      "rehandle": 4.6000000000000005,
      "resequence": 0.0,
      "sts_wait": 0.108337495,
      "transfer_wait": 0.43334997833333333,
      "truck_wait": 2.1518163416666662,
      "vessel_delay": 0.0
    },
    "total_cost": 79.11707000000003,
    "transfer_wait_s": 260.00998716464164,
    "vessel_delay_min": 0.0
  },
  {
    "action_counts": {
      "PRE_REHANDLE": 5,
      "REPOSITION": 45,
      "SERVE": 48,
      "WAIT": 21
    },
    "backlog": 0,
    "cand_feasible": {
      "PRE_REHANDLE": 94,
      "REPOSITION": 291,
      "SERVE": 105,
      "WAIT": 119
    },
    "cand_listed": {
      "PRE_REHANDLE": 109,
      "REPOSITION": 314,
      "SERVE": 108,
      "WAIT": 119
    },
    "combo_truncations": 4,
    "completion_rate": 1.0,
    "empty_travel_m": 3120.0,
    "invariants_ok": true,
    "loaded_travel_m": 13.0,
    "mean_wait_min": 0.29964267956372515,
    "n_decisions": 71,
    "p95_wait_min": 1.9220370370370499,
    "rehandles": 13,
    "seed": 420033,
    "serve_available": 98,
    "serve_taken": 48,
    "sts_wait_s": 24.942854297869417,
    "term_contrib": {
      "crane_travel": 0.013,
      "depart_delay": 0.0,
      "empty_travel": 3.1199999999999997,
      "imbalance": 0.20779,
      "interference": 17.91438077,
      "lane_cong": 42.40388892000001,
      "long_wait": 0.0,
      "rehandle": 2.6,
      "resequence": 0.0,
      "sts_wait": 0.041571423333333336,
      "transfer_wait": 0.3415714233333334,
      "truck_wait": 1.1386421833333333,
      "vessel_delay": 0.0
    },
    "total_cost": 67.780849,
    "transfer_wait_s": 204.94285429786942,
    "vessel_delay_min": 0.0
  },
  {
    "action_counts": {
      "PRE_REHANDLE": 3,
      "REPOSITION": 55,
      "SERVE": 48,
      "WAIT": 18
    },
    "backlog": 0,
    "cand_feasible": {
      "PRE_REHANDLE": 125,
      "REPOSITION": 376,
      "SERVE": 132,
      "WAIT": 124
    },
    "cand_listed": {
      "PRE_REHANDLE": 143,
      "REPOSITION": 417,
      "SERVE": 145,
      "WAIT": 124
    },
    "combo_truncations": 13,
    "completion_rate": 1.0,
    "empty_travel_m": 3594.5,
    "invariants_ok": true,
    "loaded_travel_m": 26.0,
    "mean_wait_min": 0.3362199395803662,
    "n_decisions": 76,
    "p95_wait_min": 2.9261532928385576,
    "rehandles": 16,
    "seed": 420034,
    "serve_available": 98,
    "serve_taken": 48,
    "sts_wait_s": 15.53949989389912,
    "term_contrib": {
      "crane_travel": 0.026,
      "depart_delay": 0.0,
      "empty_travel": 3.5944999999999996,
      "imbalance": 0.2351759999999999,
      "interference": 11.759430409999998,
      "lane_cong": 44.713000079999986,
      "long_wait": 0.0,
      "rehandle": 3.1999999999999997,
      "resequence": 0.0,
      "sts_wait": 0.025899166666666668,
      "transfer_wait": 0.32589916666666674,
      "truck_wait": 1.2103917816666667,
      "vessel_delay": 0.0
    },
    "total_cost": 65.090301,
    "transfer_wait_s": 195.53949989389912,
    "vessel_delay_min": 0.0
  },
  {
    "action_counts": {
      "PRE_REHANDLE": 7,
      "REPOSITION": 67,
      "SERVE": 46,
      "WAIT": 25
    },
    "backlog": 0,
    "cand_feasible": {
      "PRE_REHANDLE": 165,
      "REPOSITION": 348,
      "SERVE": 166,
      "WAIT": 145
    },
    "cand_listed": {
      "PRE_REHANDLE": 207,
      "REPOSITION": 410,
      "SERVE": 190,
      "WAIT": 145
    },
    "combo_truncations": 9,
    "completion_rate": 1.0,
    "empty_travel_m": 5947.5,
    "invariants_ok": true,
    "loaded_travel_m": 32.5,
    "mean_wait_min": 1.5506096999651202,
    "n_decisions": 93,
    "p95_wait_min": 10.293283000928614,
    "rehandles": 27,
    "seed": 420035,
    "serve_available": 114,
    "serve_taken": 46,
    "sts_wait_s": 61.3879543761941,
    "term_contrib": {
      "crane_travel": 0.0325,
      "depart_delay": 0.0,
      "empty_travel": 5.947500000000003,
      "imbalance": 0.28084700000000007,
      "interference": 15.291771180000003,
      "lane_cong": 49.18497223000001,
      "long_wait": 0.0,
      "rehandle": 5.400000000000001,
      "resequence": 0.0,
      "sts_wait": 0.10231325666666666,
      "transfer_wait": 0.40925302999999996,
      "truck_wait": 5.892316861666668,
      "vessel_delay": 0.0
    },
    "total_cost": 82.54147799999996,
    "transfer_wait_s": 245.5518175047764,
    "vessel_delay_min": 0.0
  },
  {
    "action_counts": {
      "PRE_REHANDLE": 8,
      "REPOSITION": 75,
      "SERVE": 54,
      "WAIT": 15
    },
    "backlog": 0,
    "cand_feasible": {
      "PRE_REHANDLE": 225,
      "REPOSITION": 460,
      "SERVE": 133,
      "WAIT": 152
    },
    "cand_listed": {
      "PRE_REHANDLE": 292,
      "REPOSITION": 545,
      "SERVE": 159,
      "WAIT": 152
    },
    "combo_truncations": 16,
    "completion_rate": 1.0,
    "empty_travel_m": 4920.5,
    "invariants_ok": true,
    "loaded_travel_m": 39.0,
    "mean_wait_min": 0.4726398624123504,
    "n_decisions": 102,
    "p95_wait_min": 2.3650807078741916,
    "rehandles": 26,
    "seed": 420036,
    "serve_available": 112,
    "serve_taken": 54,
    "sts_wait_s": 14.291977469376434,
    "term_contrib": {
      "crane_travel": 0.039,
      "depart_delay": 0.0,
      "empty_travel": 4.920499999999998,
      "imbalance": 0.2675320000000001,
      "interference": 3.91332578,
      "lane_cong": 55.15977782000001,
      "long_wait": 0.0,
      "rehandle": 5.200000000000002,
      "resequence": 0.0,
      "sts_wait": 0.023819961666666667,
      "transfer_wait": 0.32381996166666666,
      "truck_wait": 2.0796153950000003,
      "vessel_delay": 0.0
    },
    "total_cost": 71.927394,
    "transfer_wait_s": 194.29197746937643,
    "vessel_delay_min": 0.0
  },
  {
    "action_counts": {
      "PRE_REHANDLE": 7,
      "REPOSITION": 74,
      "SERVE": 59,
      "WAIT": 16
    },
    "backlog": 0,
    "cand_feasible": {
      "PRE_REHANDLE": 197,
      "REPOSITION": 519,
      "SERVE": 246,
      "WAIT": 156
    },
    "cand_listed": {
      "PRE_REHANDLE": 256,
      "REPOSITION": 590,
      "SERVE": 309,
      "WAIT": 156
    },
    "combo_truncations": 31,
    "completion_rate": 1.0,
    "empty_travel_m": 6305.0,
    "invariants_ok": true,
    "loaded_travel_m": 26.0,
    "mean_wait_min": 2.116249627073988,
    "n_decisions": 101,
    "p95_wait_min": 13.548825344059166,
    "rehandles": 30,
    "seed": 420037,
    "serve_available": 134,
    "serve_taken": 59,
    "sts_wait_s": 45.82661615838424,
    "term_contrib": {
      "crane_travel": 0.026,
      "depart_delay": 0.0,
      "empty_travel": 6.3050000000000015,
      "imbalance": 0.31216900000000014,
      "interference": 8.692347700000001,
      "lane_cong": 60.893222189999996,
      "long_wait": 0.0,
      "rehandle": 6.000000000000003,
      "resequence": 0.0,
      "sts_wait": 0.07637769333333333,
      "transfer_wait": 0.3763776933333334,
      "truck_wait": 10.369623173333338,
      "vessel_delay": 0.0
    },
    "total_cost": 93.05112,
    "transfer_wait_s": 225.82661615838424,
    "vessel_delay_min": 0.0
  },
  {
    "action_counts": {
      "PRE_REHANDLE": 5,
      "REPOSITION": 72,
      "SERVE": 58,
      "WAIT": 27
    },
    "backlog": 0,
    "cand_feasible": {
      "PRE_REHANDLE": 155,
      "REPOSITION": 487,
      "SERVE": 231,
      "WAIT": 162
    },
    "cand_listed": {
      "PRE_REHANDLE": 182,
      "REPOSITION": 530,
      "SERVE": 254,
      "WAIT": 162
    },
    "combo_truncations": 21,
    "completion_rate": 1.0,
    "empty_travel_m": 4901.0,
    "invariants_ok": true,
    "loaded_travel_m": 52.0,
    "mean_wait_min": 1.5003084543773408,
    "n_decisions": 99,
    "p95_wait_min": 6.625773821910555,
    "rehandles": 19,
    "seed": 420038,
    "serve_available": 134,
    "serve_taken": 58,
    "sts_wait_s": 19.42404332779097,
    "term_contrib": {
      "crane_travel": 0.052,
      "depart_delay": 0.0,
      "empty_travel": 4.900999999999995,
      "imbalance": 0.3292609999999999,
      "interference": 12.36709948,
      "lane_cong": 55.682805579999986,
      "long_wait": 0.0,
      "rehandle": 3.8000000000000003,
      "resequence": 0.0,
      "sts_wait": 0.032373405,
      "transfer_wait": 0.332373405,
      "truck_wait": 7.201480579999999,
      "vessel_delay": 0.0
    },
    "total_cost": 84.69839399999998,
    "transfer_wait_s": 199.42404332779097,
    "vessel_delay_min": 0.0
  },
  {
    "action_counts": {
      "PRE_REHANDLE": 7,
      "REPOSITION": 83,
      "SERVE": 48,
      "WAIT": 24
    },
    "backlog": 0,
    "cand_feasible": {
      "PRE_REHANDLE": 193,
      "REPOSITION": 488,
      "SERVE": 230,
      "WAIT": 162
    },
    "cand_listed": {
      "PRE_REHANDLE": 238,
      "REPOSITION": 563,
      "SERVE": 274,
      "WAIT": 162
    },
    "combo_truncations": 27,
    "completion_rate": 1.0,
    "empty_travel_m": 5824.0,
    "invariants_ok": true,
    "loaded_travel_m": 45.5,
    "mean_wait_min": 1.6382671943428353,
    "n_decisions": 104,
    "p95_wait_min": 10.183003170523625,
    "rehandles": 24,
    "seed": 420039,
    "serve_available": 134,
    "serve_taken": 48,
    "sts_wait_s": 47.046822896310914,
    "term_contrib": {
      "crane_travel": 0.0455,
      "depart_delay": 0.0,
      "empty_travel": 5.823999999999998,
      "imbalance": 0.281646,
      "interference": 9.823354650000002,
      "lane_cong": 50.282722250000006,
      "long_wait": 0.0,
      "rehandle": 4.800000000000002,
      "resequence": 0.0,
      "sts_wait": 0.07841137166666667,
      "transfer_wait": 0.3784113716666667,
      "truck_wait": 6.225415338333334,
      "vessel_delay": 0.0
    },
    "total_cost": 77.739464,
    "transfer_wait_s": 227.0468228963109,
    "vessel_delay_min": 0.0
  },
  {
    "action_counts": {
      "PRE_REHANDLE": 3,
      "REPOSITION": 67,
      "SERVE": 45,
      "WAIT": 14
    },
    "backlog": 0,
    "cand_feasible": {
      "PRE_REHANDLE": 103,
      "REPOSITION": 424,
      "SERVE": 143,
      "WAIT": 129
    },
    "cand_listed": {
      "PRE_REHANDLE": 114,
      "REPOSITION": 470,
      "SERVE": 170,
      "WAIT": 129
    },
    "combo_truncations": 13,
    "completion_rate": 1.0,
    "empty_travel_m": 5083.0,
    "invariants_ok": true,
    "loaded_travel_m": 26.0,
    "mean_wait_min": 0.6662992643597523,
    "n_decisions": 79,
    "p95_wait_min": 3.3007991073732987,
    "rehandles": 15,
    "seed": 420040,
    "serve_available": 106,
    "serve_taken": 45,
    "sts_wait_s": 19.959545870715374,
    "term_contrib": {
      "crane_travel": 0.026,
      "depart_delay": 0.0,
      "empty_travel": 5.083000000000001,
      "imbalance": 0.22808100000000003,
      "interference": 10.339822680000001,
      "lane_cong": 41.962083369999995,
      "long_wait": 0.0,
      "rehandle": 3.0,
      "resequence": 0.0,
      "sts_wait": 0.03326591,
      "transfer_wait": 0.33326591,
      "truck_wait": 2.1987875716666667,
      "vessel_delay": 0.0
    },
    "total_cost": 63.204308999999995,
    "transfer_wait_s": 199.95954587071537,
    "vessel_delay_min": 0.0
  },
  {
    "action_counts": {
      "PRE_REHANDLE": 9,
      "REPOSITION": 47,
      "SERVE": 53,
      "WAIT": 28
    },
    "backlog": 0,
    "cand_feasible": {
      "PRE_REHANDLE": 102,
      "REPOSITION": 324,
      "SERVE": 193,
      "WAIT": 137
    },
    "cand_listed": {
      "PRE_REHANDLE": 120,
      "REPOSITION": 368,
      "SERVE": 227,
      "WAIT": 137
    },
    "combo_truncations": 11,
    "completion_rate": 1.0,
    "empty_travel_m": 3581.5,
    "invariants_ok": true,
    "loaded_travel_m": 52.0,
    "mean_wait_min": 1.0067745313119076,
    "n_decisions": 83,
    "p95_wait_min": 2.9683754963228086,
    "rehandles": 23,
    "seed": 420041,
    "serve_available": 118,
    "serve_taken": 53,
    "sts_wait_s": 58.84001242364775,
    "term_contrib": {
      "crane_travel": 0.052,
      "depart_delay": 0.0,
      "empty_travel": 3.581499999999998,
      "imbalance": 0.280919,
      "interference": 13.406417670000002,
      "lane_cong": 52.73786118000001,
      "long_wait": 0.0,
      "rehandle": 4.6000000000000005,
      "resequence": 0.0,
      "sts_wait": 0.09806668666666667,
      "transfer_wait": 0.39806668666666667,
      "truck_wait": 4.329130485,
      "vessel_delay": 0.0
    },
    "total_cost": 79.48396800000002,
    "transfer_wait_s": 238.84001242364775,
    "vessel_delay_min": 0.0
  },
  {
    "action_counts": {
      "PRE_REHANDLE": 3,
      "REPOSITION": 71,
      "SERVE": 56,
      "WAIT": 23
    },
    "backlog": 0,
    "cand_feasible": {
      "PRE_REHANDLE": 180,
      "REPOSITION": 470,
      "SERVE": 156,
      "WAIT": 153
    },
    "cand_listed": {
      "PRE_REHANDLE": 213,
      "REPOSITION": 554,
      "SERVE": 188,
      "WAIT": 153
    },
    "combo_truncations": 23,
    "completion_rate": 1.0,
    "empty_travel_m": 5122.0,
    "invariants_ok": true,
    "loaded_travel_m": 39.0,
    "mean_wait_min": 0.5823742568494888,
    "n_decisions": 98,
    "p95_wait_min": 2.861562568839982,
    "rehandles": 22,
    "seed": 420042,
    "serve_available": 120,
    "serve_taken": 56,
    "sts_wait_s": 43.292409210220285,
    "term_contrib": {
      "crane_travel": 0.039,
      "depart_delay": 0.0,
      "empty_travel": 5.122,
      "imbalance": 0.29865200000000003,
      "interference": 11.37275889,
      "lane_cong": 53.71027781999999,
      "long_wait": 0.0,
      "rehandle": 4.400000000000001,
      "resequence": 0.0,
      "sts_wait": 0.072154015,
      "transfer_wait": 0.3721540133333333,
      "truck_wait": 2.7953964316666666,
      "vessel_delay": 0.0
    },
    "total_cost": 78.182397,
    "transfer_wait_s": 223.29240921022028,
    "vessel_delay_min": 0.0
  },
  {
    "action_counts": {
      "PRE_REHANDLE": 5,
      "REPOSITION": 63,
      "SERVE": 46,
      "WAIT": 21
    },
    "backlog": 0,
    "cand_feasible": {
      "PRE_REHANDLE": 135,
      "REPOSITION": 358,
      "SERVE": 131,
      "WAIT": 135
    },
    "cand_listed": {
      "PRE_REHANDLE": 164,
      "REPOSITION": 384,
      "SERVE": 141,
      "WAIT": 135
    },
    "combo_truncations": 7,
    "completion_rate": 1.0,
    "empty_travel_m": 3744.0,
    "invariants_ok": true,
    "loaded_travel_m": 26.0,
    "mean_wait_min": 0.3255081705455615,
    "n_decisions": 78,
    "p95_wait_min": 2.8982407407407362,
    "rehandles": 18,
    "seed": 420043,
    "serve_available": 112,
    "serve_taken": 46,
    "sts_wait_s": 41.509567355185936,
    "term_contrib": {
      "crane_travel": 0.026,
      "depart_delay": 0.0,
      "empty_travel": 3.743999999999999,
      "imbalance": 0.25340300000000004,
      "interference": 13.484940889999997,
      "lane_cong": 42.78061114,
      "long_wait": 0.0,
      "rehandle": 3.600000000000001,
      "resequence": 0.0,
      "sts_wait": 0.06918261166666666,
      "transfer_wait": 0.3691826116666667,
      "truck_wait": 1.2369310483333333,
      "vessel_delay": 0.0
    },
    "total_cost": 65.56425300000002,
    "transfer_wait_s": 221.50956735518594,
    "vessel_delay_min": 0.0
  },
  {
    "action_counts": {
      "PRE_REHANDLE": 5,
      "REPOSITION": 87,
      "SERVE": 58,
      "WAIT": 19
    },
    "backlog": 0,
    "cand_feasible": {
      "PRE_REHANDLE": 193,
      "REPOSITION": 560,
      "SERVE": 158,
      "WAIT": 169
    },
    "cand_listed": {
      "PRE_REHANDLE": 254,
      "REPOSITION": 694,
      "SERVE": 197,
      "WAIT": 169
    },
    "combo_truncations": 18,
    "completion_rate": 1.0,
    "empty_travel_m": 6084.0,
    "invariants_ok": true,
    "loaded_travel_m": 19.5,
    "mean_wait_min": 0.6866968203420134,
    "n_decisions": 118,
    "p95_wait_min": 3.7844244522798403,
    "rehandles": 19,
    "seed": 420044,
    "serve_available": 119,
    "serve_taken": 58,
    "sts_wait_s": 24.15084044888772,
    "term_contrib": {
      "crane_travel": 0.0195,
      "depart_delay": 0.0,
      "empty_travel": 6.083999999999999,
      "imbalance": 0.29916600000000004,
      "interference": 7.98204372,
      "lane_cong": 54.79733341999997,
      "long_wait": 0.0,
      "rehandle": 3.8000000000000003,
      "resequence": 0.0,
      "sts_wait": 0.0402514,
      "transfer_wait": 0.3402514016666667,
      "truck_wait": 3.2961447333333336,
      "vessel_delay": 0.0
    },
    "total_cost": 76.65869799999999,
    "transfer_wait_s": 204.15084044888772,
    "vessel_delay_min": 0.0
  },
  {
    "action_counts": {
      "PRE_REHANDLE": 4,
      "REPOSITION": 54,
      "SERVE": 48,
      "WAIT": 16
    },
    "backlog": 0,
    "cand_feasible": {
      "PRE_REHANDLE": 99,
      "REPOSITION": 346,
      "SERVE": 103,
      "WAIT": 122
    },
    "cand_listed": {
      "PRE_REHANDLE": 107,
      "REPOSITION": 370,
      "SERVE": 111,
      "WAIT": 122
    },
    "combo_truncations": 5,
    "completion_rate": 1.0,
    "empty_travel_m": 2613.0,
    "invariants_ok": true,
    "loaded_travel_m": 13.0,
    "mean_wait_min": 0.34985492347933445,
    "n_decisions": 71,
    "p95_wait_min": 2.784374653880332,
    "rehandles": 14,
    "seed": 420045,
    "serve_available": 91,
    "serve_taken": 48,
    "sts_wait_s": 30.84243395607791,
    "term_contrib": {
      "crane_travel": 0.013,
      "depart_delay": 0.0,
      "empty_travel": 2.6130000000000004,
      "imbalance": 0.2698599999999999,
      "interference": 11.55900184,
      "lane_cong": 43.75533337,
      "long_wait": 0.0,
      "rehandle": 2.8000000000000003,
      "resequence": 0.0,
      "sts_wait": 0.05140405666666667,
      "transfer_wait": 0.35140405666666674,
      "truck_wait": 1.3994196933333334,
      "vessel_delay": 0.0
    },
    "total_cost": 62.81242399999998,
    "transfer_wait_s": 210.8424339560779,
    "vessel_delay_min": 0.0
  },
  {
    "action_counts": {
      "PRE_REHANDLE": 6,
      "REPOSITION": 67,
      "SERVE": 51,
      "WAIT": 17
    },
    "backlog": 0,
    "cand_feasible": {
      "PRE_REHANDLE": 210,
      "REPOSITION": 431,
      "SERVE": 141,
      "WAIT": 141
    },
    "cand_listed": {
      "PRE_REHANDLE": 284,
      "REPOSITION": 545,
      "SERVE": 185,
      "WAIT": 141
    },
    "combo_truncations": 21,
    "completion_rate": 1.0,
    "empty_travel_m": 4712.5,
    "invariants_ok": true,
    "loaded_travel_m": 32.5,
    "mean_wait_min": 0.6796104566541334,
    "n_decisions": 98,
    "p95_wait_min": 4.322228757231899,
    "rehandles": 27,
    "seed": 420046,
    "serve_available": 107,
    "serve_taken": 51,
    "sts_wait_s": 43.955445699817574,
    "term_contrib": {
      "crane_travel": 0.0325,
      "depart_delay": 0.0,
      "empty_travel": 4.712499999999999,
      "imbalance": 0.2448469999999999,
      "interference": 13.631871080000002,
      "lane_cong": 53.626444479999996,
      "long_wait": 0.0,
      "rehandle": 5.400000000000002,
      "resequence": 0.0,
      "sts_wait": 0.073259075,
      "transfer_wait": 0.3732590766666667,
      "truck_wait": 2.7864028716666667,
      "vessel_delay": 0.0
    },
    "total_cost": 80.88108300000003,
    "transfer_wait_s": 223.95544569981757,
    "vessel_delay_min": 0.0
  },
  {
    "action_counts": {
      "PRE_REHANDLE": 4,
      "REPOSITION": 66,
      "SERVE": 42,
      "WAIT": 19
    },
    "backlog": 0,
    "cand_feasible": {
      "PRE_REHANDLE": 114,
      "REPOSITION": 345,
      "SERVE": 112,
      "WAIT": 131
    },
    "cand_listed": {
      "PRE_REHANDLE": 146,
      "REPOSITION": 406,
      "SERVE": 137,
      "WAIT": 131
    },
    "combo_truncations": 9,
    "completion_rate": 1.0,
    "empty_travel_m": 3783.0,
    "invariants_ok": true,
    "loaded_travel_m": 19.5,
    "mean_wait_min": 0.28480474288364815,
    "n_decisions": 87,
    "p95_wait_min": 2.4129648600264773,
    "rehandles": 14,
    "seed": 420047,
    "serve_available": 97,
    "serve_taken": 42,
    "sts_wait_s": 3.592885084231966,
    "term_contrib": {
      "crane_travel": 0.0195,
      "depart_delay": 0.0,
      "empty_travel": 3.783,
      "imbalance": 0.22172199999999997,
      "interference": 14.182828310000001,
      "lane_cong": 38.390527789999986,
      "long_wait": 0.0,
      "rehandle": 2.8000000000000003,
      "resequence": 0.0,
      "sts_wait": 0.005988141666666666,
      "transfer_wait": 0.30598814166666666,
      "truck_wait": 0.9683361283333334,
      "vessel_delay": 0.0
    },
    "total_cost": 60.67789000000001,
    "transfer_wait_s": 183.59288508423197,
    "vessel_delay_min": 0.0
  },
  {
    "action_counts": {
      "PRE_REHANDLE": 3,
      "REPOSITION": 54,
      "SERVE": 48,
      "WAIT": 12
    },
    "backlog": 0,
    "cand_feasible": {
      "PRE_REHANDLE": 88,
      "REPOSITION": 274,
      "SERVE": 98,
      "WAIT": 117
    },
    "cand_listed": {
      "PRE_REHANDLE": 113,
      "REPOSITION": 315,
      "SERVE": 108,
      "WAIT": 117
    },
    "combo_truncations": 4,
    "completion_rate": 1.0,
    "empty_travel_m": 3588.0,
    "invariants_ok": true,
    "loaded_travel_m": 32.5,
    "mean_wait_min": 0.25862139405208184,
    "n_decisions": 72,
    "p95_wait_min": 1.7483636843761892,
    "rehandles": 13,
    "seed": 420048,
    "serve_available": 92,
    "serve_taken": 48,
    "sts_wait_s": 18.45335640357098,
    "term_contrib": {
      "crane_travel": 0.0325,
      "depart_delay": 0.0,
      "empty_travel": 3.5879999999999983,
      "imbalance": 0.23103999999999997,
      "interference": 7.490896620000001,
      "lane_cong": 41.06863894000001,
      "long_wait": 0.0,
      "rehandle": 2.5999999999999996,
      "resequence": 0.0,
      "sts_wait": 0.030755595,
      "transfer_wait": 0.33075559500000007,
      "truck_wait": 0.9827612966666666,
      "vessel_delay": 0.0
    },
    "total_cost": 56.35535399999999,
    "transfer_wait_s": 198.45335640357098,
    "vessel_delay_min": 0.0
  },
  {
    "action_counts": {
      "PRE_REHANDLE": 3,
      "REPOSITION": 76,
      "SERVE": 51,
      "WAIT": 11
    },
    "backlog": 0,
    "cand_feasible": {
      "PRE_REHANDLE": 131,
      "REPOSITION": 428,
      "SERVE": 123,
      "WAIT": 141
    },
    "cand_listed": {
      "PRE_REHANDLE": 154,
      "REPOSITION": 484,
      "SERVE": 130,
      "WAIT": 141
    },
    "combo_truncations": 8,
    "completion_rate": 1.0,
    "empty_travel_m": 4595.5,
    "invariants_ok": true,
    "loaded_travel_m": 19.5,
    "mean_wait_min": 0.184117040221681,
    "n_decisions": 92,
    "p95_wait_min": 0.8125,
    "rehandles": 19,
    "seed": 420049,
    "serve_available": 107,
    "serve_taken": 51,
    "sts_wait_s": 32.300603985233465,
    "term_contrib": {
      "crane_travel": 0.0195,
      "depart_delay": 0.0,
      "empty_travel": 4.5954999999999995,
      "imbalance": 0.2790620000000001,
      "interference": 5.755436659999999,
      "lane_cong": 48.33080556000001,
      "long_wait": 0.0,
      "rehandle": 3.8,
      "resequence": 0.0,
      "sts_wait": 0.05383434,
      "transfer_wait": 0.35383434,
      "truck_wait": 0.7917032716666668,
      "vessel_delay": 0.0
    },
    "total_cost": 63.97967999999999,
    "transfer_wait_s": 212.30060398523347,
    "vessel_delay_min": 0.0
  },
  {
    "action_counts": {
      "PRE_REHANDLE": 4,
      "REPOSITION": 57,
      "SERVE": 51,
      "WAIT": 20
    },
    "backlog": 0,
    "cand_feasible": {
      "PRE_REHANDLE": 142,
      "REPOSITION": 307,
      "SERVE": 116,
      "WAIT": 132
    },
    "cand_listed": {
      "PRE_REHANDLE": 180,
      "REPOSITION": 364,
      "SERVE": 130,
      "WAIT": 132
    },
    "combo_truncations": 8,
    "completion_rate": 1.0,
    "empty_travel_m": 4238.0,
    "invariants_ok": true,
    "loaded_travel_m": 19.5,
    "mean_wait_min": 0.13713021698644523,
    "n_decisions": 87,
    "p95_wait_min": 0.3653469950560369,
    "rehandles": 20,
    "seed": 420050,
    "serve_available": 100,
    "serve_taken": 51,
    "sts_wait_s": 61.35858377016848,
    "term_contrib": {
      "crane_travel": 0.0195,
      "depart_delay": 0.0,
      "empty_travel": 4.237999999999998,
      "imbalance": 0.272805,
      "interference": 16.90730232,
      "lane_cong": 49.145500059999975,
      "long_wait": 0.0,
      "rehandle": 4.000000000000002,
      "resequence": 0.0,
      "sts_wait": 0.10226430666666667,
      "transfer_wait": 0.4090572250000001,
      "truck_wait": 0.5896599333333333,
      "vessel_delay": 0.0
    },
    "total_cost": 75.684092,
    "transfer_wait_s": 245.43433508067392,
    "vessel_delay_min": 0.0
  },
  {
    "action_counts": {
      "PRE_REHANDLE": 4,
      "REPOSITION": 63,
      "SERVE": 41,
      "WAIT": 14
    },
    "backlog": 0,
    "cand_feasible": {
      "PRE_REHANDLE": 111,
      "REPOSITION": 294,
      "SERVE": 118,
      "WAIT": 122
    },
    "cand_listed": {
      "PRE_REHANDLE": 130,
      "REPOSITION": 327,
      "SERVE": 146,
      "WAIT": 122
    },
    "combo_truncations": 5,
    "completion_rate": 1.0,
    "empty_travel_m": 4537.0,
    "invariants_ok": true,
    "loaded_travel_m": 45.5,
    "mean_wait_min": 0.6333017755772615,
    "n_decisions": 74,
    "p95_wait_min": 4.5827029298388124,
    "rehandles": 24,
    "seed": 420051,
    "serve_available": 99,
    "serve_taken": 41,
    "sts_wait_s": 38.674564960711905,
    "term_contrib": {
      "crane_travel": 0.0455,
      "depart_delay": 0.0,
      "empty_travel": 4.536999999999998,
      "imbalance": 0.25328199999999995,
      "interference": 9.99545642,
      "lane_cong": 43.59508337,
      "long_wait": 0.0,
      "rehandle": 4.800000000000001,
      "resequence": 0.0,
      "sts_wait": 0.06445760833333333,
      "transfer_wait": 0.36445760833333335,
      "truck_wait": 1.963235505,
      "vessel_delay": 0.0
    },
    "total_cost": 65.618476,
    "transfer_wait_s": 218.6745649607119,
    "vessel_delay_min": 0.0
  },
  {
    "action_counts": {
      "PRE_REHANDLE": 4,
      "REPOSITION": 57,
      "SERVE": 45,
      "WAIT": 16
    },
    "backlog": 0,
    "cand_feasible": {
      "PRE_REHANDLE": 87,
      "REPOSITION": 375,
      "SERVE": 108,
      "WAIT": 122
    },
    "cand_listed": {
      "PRE_REHANDLE": 99,
      "REPOSITION": 397,
      "SERVE": 111,
      "WAIT": 122
    },
    "combo_truncations": 9,
    "completion_rate": 1.0,
    "empty_travel_m": 2970.5,
    "invariants_ok": true,
    "loaded_travel_m": 26.0,
    "mean_wait_min": 0.24104543487084723,
    "n_decisions": 69,
    "p95_wait_min": 2.282484134939659,
    "rehandles": 12,
    "seed": 420052,
    "serve_available": 96,
    "serve_taken": 45,
    "sts_wait_s": 36.31669375085494,
    "term_contrib": {
      "crane_travel": 0.026,
      "depart_delay": 0.0,
      "empty_travel": 2.9704999999999986,
      "imbalance": 0.22622899999999993,
      "interference": 8.42855527,
      "lane_cong": 39.394833359999986,
      "long_wait": 0.0,
      "rehandle": 2.4,
      "resequence": 0.0,
      "sts_wait": 0.060527823333333335,
      "transfer_wait": 0.36052782333333333,
      "truck_wait": 0.8436590233333333,
      "vessel_delay": 0.0
    },
    "total_cost": 54.710836,
    "transfer_wait_s": 216.31669375085494,
    "vessel_delay_min": 0.0
  },
  {
    "action_counts": {
      "PRE_REHANDLE": 2,
      "REPOSITION": 89,
      "SERVE": 50,
      "WAIT": 37
    },
    "backlog": 0,
    "cand_feasible": {
      "PRE_REHANDLE": 210,
      "REPOSITION": 629,
      "SERVE": 223,
      "WAIT": 178
    },
    "cand_listed": {
      "PRE_REHANDLE": 231,
      "REPOSITION": 658,
      "SERVE": 233,
      "WAIT": 178
    },
    "combo_truncations": 38,
    "completion_rate": 1.0,
    "empty_travel_m": 3809.0,
    "invariants_ok": true,
    "loaded_travel_m": 13.0,
    "mean_wait_min": 0.5171118656051917,
    "n_decisions": 101,
    "p95_wait_min": 2.3030634459281525,
    "rehandles": 20,
    "seed": 420053,
    "serve_available": 151,
    "serve_taken": 50,
    "sts_wait_s": 41.12899625863065,
    "term_contrib": {
      "crane_travel": 0.013,
      "depart_delay": 0.0,
      "empty_travel": 3.8089999999999993,
      "imbalance": 0.285422,
      "interference": 19.762849219999993,
      "lane_cong": 47.06416675000001,
      "long_wait": 0.0,
      "rehandle": 4.0,
      "resequence": 0.0,
      "sts_wait": 0.06854832666666667,
      "transfer_wait": 0.3685483266666667,
      "truck_wait": 2.1718698383333335,
      "vessel_delay": 0.0
    },
    "total_cost": 77.54341199999999,
    "transfer_wait_s": 221.12899625863065,
    "vessel_delay_min": 0.0
  },
  {
    "action_counts": {
      "PRE_REHANDLE": 3,
      "REPOSITION": 61,
      "SERVE": 54,
      "WAIT": 25
    },
    "backlog": 0,
    "cand_feasible": {
      "PRE_REHANDLE": 147,
      "REPOSITION": 437,
      "SERVE": 198,
      "WAIT": 143
    },
    "cand_listed": {
      "PRE_REHANDLE": 178,
      "REPOSITION": 499,
      "SERVE": 223,
      "WAIT": 143
    },
    "combo_truncations": 19,
    "completion_rate": 1.0,
    "empty_travel_m": 4966.0,
    "invariants_ok": true,
    "loaded_travel_m": 26.0,
    "mean_wait_min": 1.6751187886471373,
    "n_decisions": 87,
    "p95_wait_min": 6.961940915639032,
    "rehandles": 20,
    "seed": 420054,
    "serve_available": 116,
    "serve_taken": 54,
    "sts_wait_s": 25.133923418493396,
    "term_contrib": {
      "crane_travel": 0.026,
      "depart_delay": 0.0,
      "empty_travel": 4.9659999999999975,
      "imbalance": 0.316857,
      "interference": 18.16244566,
      "lane_cong": 52.26711115,
      "long_wait": 0.0,
      "rehandle": 4.000000000000001,
      "resequence": 0.0,
      "sts_wait": 0.04188987333333333,
      "transfer_wait": 0.3418898716666667,
      "truck_wait": 7.37052267,
      "vessel_delay": 0.0
    },
    "total_cost": 87.49271499999998,
    "transfer_wait_s": 205.1339234184934,
    "vessel_delay_min": 0.0
  },
  {
    "action_counts": {
      "PRE_REHANDLE": 3,
      "REPOSITION": 64,
      "SERVE": 42,
      "WAIT": 20
    },
    "backlog": 0,
    "cand_feasible": {
      "PRE_REHANDLE": 189,
      "REPOSITION": 410,
      "SERVE": 124,
      "WAIT": 129
    },
    "cand_listed": {
      "PRE_REHANDLE": 218,
      "REPOSITION": 448,
      "SERVE": 142,
      "WAIT": 129
    },
    "combo_truncations": 19,
    "completion_rate": 1.0,
    "empty_travel_m": 4257.5,
    "invariants_ok": true,
    "loaded_travel_m": 39.0,
    "mean_wait_min": 0.6929962786045198,
    "n_decisions": 79,
    "p95_wait_min": 5.543998229692997,
    "rehandles": 23,
    "seed": 420055,
    "serve_available": 95,
    "serve_taken": 42,
    "sts_wait_s": 49.30099748413613,
    "term_contrib": {
      "crane_travel": 0.039,
      "depart_delay": 0.0,
      "empty_travel": 4.257500000000003,
      "imbalance": 0.286738,
      "interference": 8.2617909,
      "lane_cong": 44.80975004,
      "long_wait": 0.0,
      "rehandle": 4.600000000000001,
      "resequence": 0.0,
      "sts_wait": 0.08216832833333333,
      "transfer_wait": 0.38216832833333336,
      "truck_wait": 2.3561873466666667,
      "vessel_delay": 0.0
    },
    "total_cost": 65.075303,
    "transfer_wait_s": 229.30099748413613,
    "vessel_delay_min": 0.0
  },
  {
    "action_counts": {
      "PRE_REHANDLE": 6,
      "REPOSITION": 74,
      "SERVE": 58,
      "WAIT": 20
    },
    "backlog": 0,
    "cand_feasible": {
      "PRE_REHANDLE": 90,
      "REPOSITION": 475,
      "SERVE": 184,
      "WAIT": 158
    },
    "cand_listed": {
      "PRE_REHANDLE": 120,
      "REPOSITION": 554,
      "SERVE": 211,
      "WAIT": 158
    },
    "combo_truncations": 13,
    "completion_rate": 1.0,
    "empty_travel_m": 4459.0,
    "invariants_ok": true,
    "loaded_travel_m": 26.0,
    "mean_wait_min": 1.0954737008622426,
    "n_decisions": 101,
    "p95_wait_min": 4.417394760243481,
    "rehandles": 19,
    "seed": 420056,
    "serve_available": 132,
    "serve_taken": 58,
    "sts_wait_s": 21.986926136670263,
    "term_contrib": {
      "crane_travel": 0.026,
      "depart_delay": 0.0,
      "empty_travel": 4.458999999999997,
      "imbalance": 0.289476,
      "interference": 12.434549789999998,
      "lane_cong": 52.641555600000004,
      "long_wait": 0.0,
      "rehandle": 3.8,
      "resequence": 0.0,
      "sts_wait": 0.036644876666666666,
      "transfer_wait": 0.33664487833333334,
      "truck_wait": 5.258273768333334,
      "vessel_delay": 0.0
    },
    "total_cost": 79.28214600000004,
    "transfer_wait_s": 201.98692613667026,
    "vessel_delay_min": 0.0
  },
  {
    "action_counts": {
      "PRE_REHANDLE": 4,
      "REPOSITION": 54,
      "SERVE": 46,
      "WAIT": 11
    },
    "backlog": 0,
    "cand_feasible": {
      "PRE_REHANDLE": 95,
      "REPOSITION": 324,
      "SERVE": 116,
      "WAIT": 115
    },
    "cand_listed": {
      "PRE_REHANDLE": 117,
      "REPOSITION": 358,
      "SERVE": 130,
      "WAIT": 115
    },
    "combo_truncations": 5,
    "completion_rate": 1.0,
    "empty_travel_m": 3510.0,
    "invariants_ok": true,
    "loaded_travel_m": 58.5,
    "mean_wait_min": 0.6608675087906132,
    "n_decisions": 70,
    "p95_wait_min": 4.374766651943113,
    "rehandles": 21,
    "seed": 420057,
    "serve_available": 94,
    "serve_taken": 46,
    "sts_wait_s": 43.3980573924764,
    "term_contrib": {
      "crane_travel": 0.058499999999999996,
      "depart_delay": 0.0,
      "empty_travel": 3.5099999999999993,
      "imbalance": 0.22897300000000004,
      "interference": 5.119672189999999,
      "lane_cong": 44.91505556999999,
      "long_wait": 0.0,
      "rehandle": 4.200000000000001,
      "resequence": 0.0,
      "sts_wait": 0.07233009666666666,
      "transfer_wait": 0.37233009666666667,
      "truck_wait": 2.3791230299999997,
      "vessel_delay": 0.0
    },
    "total_cost": 60.85598600000002,
    "transfer_wait_s": 223.3980573924764,
    "vessel_delay_min": 0.0
  },
  {
    "action_counts": {
      "PRE_REHANDLE": 10,
      "REPOSITION": 71,
      "SERVE": 56,
      "WAIT": 22
    },
    "backlog": 0,
    "cand_feasible": {
      "PRE_REHANDLE": 197,
      "REPOSITION": 406,
      "SERVE": 236,
      "WAIT": 159
    },
    "cand_listed": {
      "PRE_REHANDLE": 250,
      "REPOSITION": 480,
      "SERVE": 273,
      "WAIT": 159
    },
    "combo_truncations": 15,
    "completion_rate": 1.0,
    "empty_travel_m": 6181.5,
    "invariants_ok": true,
    "loaded_travel_m": 45.5,
    "mean_wait_min": 1.6935455861678366,
    "n_decisions": 102,
    "p95_wait_min": 6.7085486321947085,
    "rehandles": 27,
    "seed": 420058,
    "serve_available": 128,
    "serve_taken": 56,
    "sts_wait_s": 30.69211606414683,
    "term_contrib": {
      "crane_travel": 0.0455,
      "depart_delay": 0.0,
      "empty_travel": 6.181500000000001,
      "imbalance": 0.3109429999999999,
      "interference": 8.89743076,
      "lane_cong": 57.63700008999999,
      "long_wait": 0.0,
      "rehandle": 5.400000000000001,
      "resequence": 0.0,
      "sts_wait": 0.051153526666666664,
      "transfer_wait": 0.35115352666666666,
      "truck_wait": 7.790309700000001,
      "vessel_delay": 0.0
    },
    "total_cost": 86.66499499999999,
    "transfer_wait_s": 210.69211606414683,
    "vessel_delay_min": 0.0
  },
  {
    "action_counts": {
      "PRE_REHANDLE": 2,
      "REPOSITION": 66,
      "SERVE": 52,
      "WAIT": 23
    },
    "backlog": 0,
    "cand_feasible": {
      "PRE_REHANDLE": 185,
      "REPOSITION": 492,
      "SERVE": 175,
      "WAIT": 143
    },
    "cand_listed": {
      "PRE_REHANDLE": 220,
      "REPOSITION": 559,
      "SERVE": 207,
      "WAIT": 143
    },
    "combo_truncations": 18,
    "completion_rate": 1.0,
    "empty_travel_m": 5115.5,
    "invariants_ok": true,
    "loaded_travel_m": 19.5,
    "mean_wait_min": 1.650166687930619,
    "n_decisions": 94,
    "p95_wait_min": 10.891776869843527,
    "rehandles": 26,
    "seed": 420059,
    "serve_available": 105,
    "serve_taken": 52,
    "sts_wait_s": 46.103087269664684,
    "term_contrib": {
      "crane_travel": 0.0195,
      "depart_delay": 0.0,
      "empty_travel": 5.115499999999999,
      "imbalance": 0.3010730000000001,
      "interference": 11.070184480000002,
      "lane_cong": 54.34950004,
      "long_wait": 0.0,
      "rehandle": 5.200000000000001,
      "resequence": 0.0,
      "sts_wait": 0.07683847833333333,
      "transfer_wait": 0.37683847833333334,
      "truck_wait": 6.60066675,
      "vessel_delay": 0.0
    },
    "total_cost": 83.11010400000002,
    "transfer_wait_s": 226.10308726966468,
    "vessel_delay_min": 0.0
  }
]